Metadata-Version: 2.1
Name: squarecloud
Version: 1.4
Summary: Este módulo foi desenvolvido com o intuito de auxiliar as pessoas de coletar informações relacionadas as suas aplicações hospedadas na https://squarecloud.app!
Home-page: https://github.com/squarecl/square-python-status
Author: NemRela
License: Apache-2.0
Project-URL: Bug Hunter, https://github.com/squarecl/square-python-status/issues
Project-URL: Documentation, https://github.com/squarecl/square-python-status
Keywords: squarecloud,square cloud,square-python-status,square
Platform: UNKNOWN
Classifier: Development Status :: 3 - Alpha
Classifier: Intended Audience :: Developers
Classifier: License :: OSI Approved :: Apache Software License
Classifier: Programming Language :: Python :: 3.9
Classifier: Programming Language :: Python :: 3.10
Classifier: Operating System :: POSIX :: Linux
Requires-Python: >=3.6.0
License-File: LICENSE
